presidio_analyzer/__init__.py
presidio_analyzer/analysis_explanation.py
presidio_analyzer/analyzer_engine.py
presidio_analyzer/analyzer_request.py
presidio_analyzer/app_tracer.py
presidio_analyzer/batch_analyzer_engine.py
presidio_analyzer/dict_analyzer_result.py
presidio_analyzer/entity_recognizer.py
presidio_analyzer/local_recognizer.py
presidio_analyzer/pattern.py
presidio_analyzer/pattern_recognizer.py
presidio_analyzer/recognizer_registry.py
presidio_analyzer/recognizer_result.py
presidio_analyzer/remote_recognizer.py
presidio_analyzer/context_aware_enhancers/__init__.py
presidio_analyzer/context_aware_enhancers/context_aware_enhancer.py
presidio_analyzer/context_aware_enhancers/lemma_context_aware_enhancer.py
presidio_analyzer/nlp_engine/__init__.py
presidio_analyzer/nlp_engine/ner_model_configuration.py
presidio_analyzer/nlp_engine/nlp_artifacts.py
presidio_analyzer/nlp_engine/nlp_engine.py
presidio_analyzer/nlp_engine/nlp_engine_provider.py
presidio_analyzer/nlp_engine/spacy_nlp_engine.py
presidio_analyzer/nlp_engine/stanza_nlp_engine.py
presidio_analyzer/nlp_engine/transformers_nlp_engine.py
presidio_analyzer/predefined_recognizers/__init__.py
presidio_analyzer/predefined_recognizers/aba_routing_recognizer.py
presidio_analyzer/predefined_recognizers/au_abn_recognizer.py
presidio_analyzer/predefined_recognizers/au_acn_recognizer.py
presidio_analyzer/predefined_recognizers/au_medicare_recognizer.py
presidio_analyzer/predefined_recognizers/au_tfn_recognizer.py
presidio_analyzer/predefined_recognizers/azure_ai_language.py
presidio_analyzer/predefined_recognizers/credit_card_recognizer.py
presidio_analyzer/predefined_recognizers/crypto_recognizer.py
presidio_analyzer/predefined_recognizers/date_recognizer.py
presidio_analyzer/predefined_recognizers/email_recognizer.py
presidio_analyzer/predefined_recognizers/es_nif_recognizer.py
presidio_analyzer/predefined_recognizers/iban_patterns.py
presidio_analyzer/predefined_recognizers/iban_recognizer.py
presidio_analyzer-2.2.352.dist-info/METADATA
presidio_analyzer-2.2.352.dist-info/WHEEL
presidio_analyzer-2.2.352.dist-info/top_level.txt
presidio_analyzer-2.2.352.dist-info/RECORD
