Metadata-Version: 2.1
Name: presidio-analyzer
Version: 2.2.352
Summary: Presidio analyzer package
Home-page: https://github.com/Microsoft/presidio
License: MIT
Classifier: License :: OSI Approved :: MIT License
Classifier: Operating System :: OS Independent
Classifier: Programming Language :: Python :: 3.7
Classifier: Programming Language :: Python :: 3.8
Classifier: Programming Language :: Python :: 3.9
Classifier: Programming Language :: Python :: 3.10
Classifier: Programming Language :: Python :: 3.11
Requires-Dist: spacy <4.0.0,>=3.4.4
Requires-Dist: regex
Requires-Dist: tldextract
Requires-Dist: pyyaml
Requires-Dist: phonenumbers <9.0.0,>=8.12
Provides-Extra: azure-ai-language
Requires-Dist: azure-ai-textanalytics ; extra == 'azure-ai-language'
Requires-Dist: azure-core ; extra == 'azure-ai-language'
Provides-Extra: stanza
Requires-Dist: stanza ; extra == 'stanza'
Requires-Dist: spacy-stanza ; extra == 'stanza'
Provides-Extra: transformers
Requires-Dist: spacy-huggingface-pipelines ; extra == 'transformers'
